mcfly_test/__init__.py
mcfly_test/py.typed
mcfly_test-0.0.0.dist-info/METADATA
mcfly_test-0.0.0.dist-info/WHEEL
mcfly_test-0.0.0.dist-info/RECORD
