Metadata-Version: 2.1
Name: mcfly_test
Version: 0.0.0
Summary: 
Home-page: https://gitlab.com/lukin0110/poetry-copier-package-test-gitlab/
License: Proprietary
Requires-Python: >=3.11.6,<4.0
Classifier: License :: Other/Proprietary License
Classifier: Programming Language :: Python :: 3
Classifier: Programming Language :: Python :: 3.12
Requires-Dist: poethepoet (>=0.24.4)
Project-URL: Repository, https://gitlab.com/lukin0110/poetry-copier-package-test-gitlab/
